{
	"info": {
		"_postman_id": "64577ae6-aae7-4400-8072-65574c65861b",
		"name": "People Manager API",
		"schema": "https://schema.getpostman.com/json/collection/v2.1.0/collection.json",
		"_exporter_id": "30515867"
	},
	"item": [
		{
			"name": "People",
			"item": [
				{
					"name": "Get by ID",
					"request": {
						"method": "GET",
						"header": [],
						"url": {
							"raw": "http://localhost:8080/person/1",
							"protocol": "http",
							"host": [
								"localhost"
							],
							"port": "8080",
							"path": [
								"person",
								"1"
							]
						}
					},
					"response": []
				},
				{
					"name": "Create",
					"request": {
						"method": "POST",
						"header": [],
						"body": {
							"mode": "raw",
							"raw": "{\r\n  \"name\": \"string\",\r\n  \"email\": \"string\",\r\n  \"cpf\": \"string\",\r\n  \"birthDate\": \"2024-07-20\"\r\n}",
							"options": {
								"raw": {
									"language": "json"
								}
							}
						},
						"url": {
							"raw": "http://localhost:8080/person/",
							"protocol": "http",
							"host": [
								"localhost"
							],
							"port": "8080",
							"path": [
								"person",
								""
							]
						}
					},
					"response": []
				}
			]
		}
	]
}